{
  "id": "tag:search.twitter.com,2005:418130988250570752",
  "objectType": "activity",
  "actor": {
    "id": "id:twitter.com:17200003",
    "displayName": "jimmoffitt",
    "postedTime": "2008-11-05T23:06:37.000Z",
    "summary": "Hi world. Love family, water, snow, music, travel, photography, food, learning, user interfaces, solving problems.",
    "friendsCount": 85,
    "followersCount": 80,
    "location": {
      "displayName": "Longmont, Colorado"
    }
  },
  "verb": "post",
  "postedTime": "2013-12-31T21:26:10.000Z",
  "body": "Generating a sample tweet for documentation. \nhttps:\/\/t.co\/UpVhmiFDAv\nhttps:\/\/t.co\/OY7MlhFsGB\n@thisuser @thatuser\n#HappyNewYear #Ruby",
  "object": {
    "id": "object:search.twitter.com,2005:418130988250570752"
  },
  "gnip": {
    "matching_rules": [
      {
        "value": "#Ruby",
        "tag": "software-languages"
      }
    ],
    "urls": [
      {
        "expanded_url": "https:\/\/github.com\/jimmoffitt\/pt-dm\/blob\/master\/ReadMe.md"
      }
    ],
    "profileLocations": [
      {
        "address": {
          "country": "United States",
          "countryCode": "US",
          "locality": "Longmont",
          "region": "Colorado",
          "subRegion": "Boulder County"
        }
      }
    ]
  }
}